README
setup.py
pyDOE/__init__.py
pyDOE/build_regression_matrix.py
pyDOE/doe_box_behnken.py
pyDOE/doe_composite.py
pyDOE/doe_factorial.py
pyDOE/doe_fold.py
pyDOE/doe_lhs.py
pyDOE/doe_plackett_burman.py
pyDOE/doe_repeat_center.py
pyDOE/doe_star.py
pyDOE/doe_union.py
pyDOE/var_regression_matrix.py
pyDOE.egg-info/PKG-INFO
pyDOE.egg-info/SOURCES.txt
pyDOE.egg-info/dependency_links.txt
pyDOE.egg-info/requires.txt
pyDOE.egg-info/top_level.txt